valor/__init__.py
valor-0.0.0.dist-info/METADATA
valor-0.0.0.dist-info/RECORD
valor-0.0.0.dist-info/WHEEL
valor-0.0.0.dist-info/top_level.txt
