Metadata-Version: 2.1
Name: valor
Version: 0.0.0
Summary: valor library.
Home-page: UNKNOWN
Author: Dr. Ford
Author-email: UNKNOWN
License: GPLv3
Platform: UNKNOWN
Classifier: Development Status :: 4 - Beta
Classifier: Programming Language :: Python :: 3
